DataPath/modules/mux.v

module multiplexador (
    input             control, // 0 = input1; 1 =input2
    input      [31:0] input1,  // Entrada 0
    input      [31:0] input2,  // Entrada 1
    output reg [31:0] saida    // Saída selecionada
);

    always @(*) begin
        if (control)
            saida = input2;
        else
            saida = input1;
    end

endmodule

DataPath/BancoDeMemoria.v
module mem (
    input             clk,          // Clock
    input             memread,      // 1 = lê da memória (lb)
    input             memwrite,     // 1 = escreve na memória (sb)
    input      [31:0] alu_resultado, // Endereço calculado pela ALU
    input      [31:0] write_data,   // Dado a ser escrito (usamos só [7:0])
    output reg [31:0] mem_read      // Dado lido (byte com extensão de sinal)
);

    reg [7:0] memoria [0:127]; // Memória byte a byte, 128 posições

    integer i;
    initial begin
        $readmemb("memorias/memoria.txt", memoria);
    end

    always @(*) begin
        if (memread)
            // Extensão de sinal: replica o bit 7 (MSB do byte) nos 24 bits superiores
            mem_read = {{24{memoria[alu_resultado[6:0]][7]}}, memoria[alu_resultado[6:0]]};
        else
            mem_read = 32'b0;
    end

    always @(posedge clk) begin
        if (memwrite)
            memoria[alu_resultado[6:0]] <= write_data[7:0];
    end

endmodule

DataPath/modules/ALU.v
module ALU (
    input      [31:0] read1,      // Operando 1 (sempre rs1)
    input      [31:0] read2_Imm,  // Operando 2 (rs2 ou imediato, já selecionado pelo mux)
    input      [3:0]  alucontrol, // Operação a executar
    output reg [31:0] alusaida,   // Resultado da operação
    output            zero        // 1 se alusaida == 0 (para beq)
);

    always @(*) begin
        casex (alucontrol)
            4'b0000: alusaida = read1 & read2_Imm;  // AND
            4'b0001: alusaida = read1 | read2_Imm;  // OR (ori)
            4'b0010: alusaida = read1 + read2_Imm;  // ADD (lb, sb — cálculo de endereço)
            4'b0110: alusaida = read1 - read2_Imm;  // SUB (sub, beq)
            4'b1000: alusaida = read1 >> read2_Imm; // SRL (shift right logical)
            default: alusaida = 32'b0;
        endcase
    end

    assign zero = (alusaida == 32'b0) ? 1'b1 : 1'b0;

endmodule

DataPath/modules/control_ALUcontrol.v
module Control (
    input [6:0] opcode,  
    output reg branch,   
    output reg memread,  
    output reg memtoreg, 
    output reg memwrite, 
    output reg alusrc,   
    output reg regwrite,
    output reg [1:0] aluop     
);

    always @(*) begin
        case (opcode)

            // lb: tipo I
            7'b0000011: begin
                branch   = 1'b0;
                memread  = 1'b1; 
                memtoreg = 1'b1; 
                aluop    = 2'b00; 
                memwrite = 1'b0;
                alusrc   = 1'b1; 
                regwrite = 1'b1; 
            end

            // sb: tipo S
            7'b0100011: begin
                branch   = 1'b0;
                memread  = 1'b0;
                memtoreg = 1'b0;
                aluop    = 2'b00;
                memwrite = 1'b1; 
                alusrc   = 1'b1; 
                regwrite = 1'b0; 
            end

            // Tipo R: sub, and, srl
            7'b0110011: begin
                branch   = 1'b0;
                memread  = 1'b0;
                memtoreg = 1'b0; 
                aluop    = 2'b10;
                memwrite = 1'b0;
                alusrc   = 1'b0; 
                regwrite = 1'b1; 
            end

            // Tipo I com imediato: ori
            7'b0010011: begin
                branch   = 1'b0;
                memread  = 1'b0;
                memtoreg = 1'b0;
                aluop    = 2'b10; 
                memwrite = 1'b0;
                alusrc   = 1'b1; 
                regwrite = 1'b1;
            end

            // beq: tipo B
            7'b1100011: begin
                branch   = 1'b1;
                memread  = 1'b0;
                memtoreg = 1'b0; 
                aluop    = 2'b01; 
                memwrite = 1'b0;
                alusrc   = 1'b0; 
                regwrite = 1'b0;
            end

            // Default: NOP
            default: begin
                branch   = 1'b0;
                memread  = 1'b0;
                memtoreg = 1'b0;
                aluop    = 2'b00;
                memwrite = 1'b0;
                alusrc   = 1'b0;
                regwrite = 1'b0;
            end

        endcase
    end

endmodule


// ========================
// Tabela de alucontrol:
//   0000= and
//   0001= or 
//   0010= add 
//   0110= sub 
//   1000= srl 
// ========================
module ALUControl (
    input [2:0] funct3,
    input funct7_b30, 
    input [1:0] aluop, 
    output reg [3:0] alucontrol 
);

    //concatenamos aluop, funct3 e o bit30 da funct7
    wire [5:0] funct;
    assign funct = {aluop, funct3, funct7_b30};


    always @(*) begin
        casex (funct)
            // aluop=00 memória, ALU soma endereço
            6'b00xxxx: alucontrol = 4'b0010;

            // aluop=01 beq: ALU subtrai e compara
            6'b01xxxx: alucontrol = 4'b0110; 

            // sub: funct3=000, funct7[30]=1
            6'b10_000_1: alucontrol = 4'b0110; 

            // and: funct3=111, funct7[30]=0
            6'b10_111_0: alucontrol = 4'b0000; 

            // ori: funct3=110 funct7[30]=x
            6'b10_110_x: alucontrol = 4'b0001; 

            // srl: funct3=101, funct7[30]=0
            6'b10_101_0: alucontrol = 4'b1000; 

            default:    alucontrol = 4'b0010; //add
        endcase
    end

endmodule

DataPath/modules/immGen.v
module ImmGen (
    input      [31:0] instruction,   // Instrução completa de 32 bits
    output reg [31:0] imm_extendido  // Imediato com extensão de sinal (32 bits)
);

    always @(*) begin
        case (instruction[6:0])

            // Tipo B: beq 
            // Imediato = [31][7][30:25][11:8],
            7'b1100011: begin
                imm_extendido = {{20{instruction[31]}},
                                  instruction[7],
                                  instruction[30:25],
                                  instruction[11:8],
                                  1'b0};
            end

            // Tipo I: lb e ori
            // Imediato = [31:20]
            7'b0000011,
            7'b0010011: begin
                imm_extendido = {{20{instruction[31]}}, instruction[31:20]};
            end

            // Tipo S: sb
            // Imediato = [31:25] e [11:7]
            7'b0100011: begin
                imm_extendido = {{20{instruction[31]}},
                                  instruction[31:25],
                                  instruction[11:7]};
            end

            // instruções sem imediato (tipo R: sub, and, srl)
            default: begin
                imm_extendido = 32'b0;
            end

        endcase
    end

endmodule

DataPath/BancoDeRegistradores.v
module BancoReg (
    input             clk,        // Clock
    input             regwrite,   // Habilitação de escrita (1 = escreve em rd)
    input      [4:0]  rs1,        // Índice do registrador fonte 1
    input      [4:0]  rs2,        // Índice do registrador fonte 2
    input      [4:0]  rd,         // Índice do registrador destino
    input      [31:0] write_data, // Dado a ser escrito em rd
    output reg [31:0] read1,      // Valor lido de rs1
    output reg [31:0] read2       // Valor lido de rs2
);


    reg [31:0] regs [0:31]; // 32 registradores de 32 bits

    integer i;
    initial begin
        // Inicializa todos os registradores com zero
        for (i = 0; i < 32; i = i + 1)
            regs[i] = 32'b0;
        // Se quiser pré-carregar valores (ex: para testes sem ADDI),
        // descomente a linha abaixo e crie o arquivo:
        // $readmemh("registradores.txt", regs);
    end

    // Leitura combinacional (sem clock) — qualquer mudança em rs1/rs2
    // reflete imediatamente na saída
    always @(*) begin
        read1 = (rs1 == 5'b0) ? 32'b0 : regs[rs1]; // x0 sempre retorna 0
        read2 = (rs2 == 5'b0) ? 32'b0 : regs[rs2];
    end

    // Escrita síncrona na borda de subida do clock
    always @(posedge clk) begin
        if (regwrite && rd != 5'b0) begin // Nunca escreve em x0
            regs[rd] <= write_data;
        end
    end

endmodule

DataPath/instructionMemory.v
module instruction_memory (
    input      [31:0] pc,          // Endereço da instrução atual
    output     [31:0] instruction  // Instrução de 32 bits lida
);

    // Memória com 32 posições de 32 bits cada (32 instruções no máximo)
    reg [31:0] rom [0:31];

    initial begin
        // CORREÇÃO: Nome do arquivo corrigido para um padrão claro.
        // O arquivo deve ter uma instrução de 32 bits por linha, em binário.
        $readmemb("memorias/instrucoes.txt", rom);
    end

    // PC vem em bytes (0, 4, 8...), dividimos por 4 para acessar índice (0, 1, 2...)
    assign instruction = rom[pc >> 2];

endmodule

DataPath/modules/programCounter.v
module program_counter (
    input             clk,      // Clock do processador
    input             reset,    // Reset síncrono (1 = volta para endereço 0)
    input      [31:0] next_pc,  // Próximo valor do PC (calculado no datapath)
    output reg [31:0] pc        // Endereço atual sendo executado
);

    always @(posedge clk) begin
        if (reset)
            pc <= 32'b0;       // Volta ao início do programa
        else
            pc <= next_pc;     // Avança para a próxima instrução
    end

endmodule

DataPath/dataPath.v
`include "programCounter.v"
`include "instructionMemory.v"
`include "control_ALUcontrol.v"
`include "BancoDeRegistradores.v"
`include "immGen.v"
`include "mux.v"
`include "ALU.v"
`include "BancoDeMemoria.v"

module data_path (
    input clk,   // Clock do processador
    input reset  // Reset: volta PC para 0
);
    wire [31:0] next_pc; // Próximo endereço
    wire [31:0] pc;      // Endereço atual

    program_counter pc_module (
        .clk(clk),
        .reset(reset),
        .next_pc(next_pc),
        .pc(pc)
    );

    wire [31:0] instruction;
    instruction_memory instruction_mem (
        .pc(pc),
        .instruction(instruction)
    );


    //Sinais de controle
    wire branch, memread, memtoreg, memwrite, alusrc, regwrite;
    wire [1:0]  aluOp;
    Control control (
        .opcode(instruction[6:0]),
        .branch(branch),
        .memread(memread),
        .memtoreg(memtoreg),
        .memwrite(memwrite),
        .alusrc(alusrc),
        .regwrite(regwrite),
        .aluop(aluOp)
    );


    wire [31:0] write_data; // Dado que será escrito em rd (vem do mux2)
    wire [31:0] read_1, read_2;
    BancoReg banco_de_registradores (
        .clk       (clk),
        .regwrite  (regwrite),
        .rs1       (instruction[19:15]),
        .rs2       (instruction[24:20]),
        .rd        (instruction[11:7]),
        .write_data(write_data),
        .read1     (read_1),
        .read2     (read_2)
    );


    wire [31:0] imm_extendido;
    ImmGen ImmGen_inst (
        .instruction  (instruction),
        .imm_extendido(imm_extendido)
    );


    wire [31:0] alu_operando2;
    multiplexador mux_alusrc (
        .control(alusrc),
        .input1(read_2),         // 0 = usa rs2 (tipo R, beq)
        .input2(imm_extendido),  // 1 = usa imediato (lb, sb, ori)
        .saida(alu_operando2)
    );


    wire [3:0] aluControl;
    ALUControl alu_control (
        .funct3(instruction[14:12]),
        .funct7_b30(instruction[30]),
        .aluop(aluOp),
        .alucontrol(aluControl)
    );


    wire [31:0] alusaida;
    wire zero;
    ALU alu (
        .read1(read_1),
        .read2_Imm(alu_operando2),
        .alucontrol(aluControl),
        .alusaida(alusaida),
        .zero(zero)
    );


    wire [31:0] memread_valor;
    mem memory_bank (
        .clk(clk),
        .memread(memread),
        .memwrite(memwrite),
        .alu_resultado(alusaida),
        .write_data(read_2),      // sb escreve o valor de rs2
        .mem_read(memread_valor)
    );


    multiplexador mux_memtoreg (
        .control(memtoreg),
        .input1(alusaida),      // 0 = resultado da ALU (tipo R, ori)
        .input2(memread_value), // 1 = dado lido da memória (lb)
        .saida(write_data)
    );


    assign next_pc = (branch && zero) ? (pc + imm_extendido) : (pc + 4);

endmodule

DataPath/testbench.v
// =============================================================================
// Testbench: RISC-V Grupo 4
//
// Programa de teste (4 instruções):
//   PC=0:  beq  x1, x0, -2    → x1≠0 → NÃO desvia, vai para PC=4
//   PC=4:  sub  x5, x5, x6    → x5 = x5 - x6
//   PC=8:  and  x7, x8, x9    → x7 = x8 & x9
//   PC=12: srl  x10, x11, x12 → x10 = x11 >> x12
//
// Para rodar: make sim
// =============================================================================

`timescale 1ns/1ps
`include "dataPath.v"

module testbench;

    reg clk;
    reg reset;

    // CORREÇÃO: reset já começa em 1 na declaração, antes de qualquer borda
    // de clock. Isso garante que o PC zera corretamente no primeiro ciclo.
    initial clk  = 0;
    initial reset = 1;          // <-- inicia em 1 direto, sem esperar clock

    always #5 clk = ~clk;

    data_path dut (
        .clk  (clk),
        .reset(reset)
    );

    integer i;

    initial begin
        // Aguarda a primeira borda para garantir que o PC síncrono vá para 0
        @(posedge clk); #1;
        
        // Libera o reset aqui! Assim, na próxima borda, o PC já poderá
        // calcular o next_pc (PC + 4) em vez de ficar preso em 0 de novo.
        reset = 0;              

        // Executa as instruções
        repeat(6) begin
            @(posedge clk); #1;
        end

        // Imprime os registradores
        for (i = 0; i < 32; i = i + 1)
            $display("Register [ %2d]:    %0d", i, dut.banco_de_registradores.regs[i]);
        $finish;
    end
    
endmodule

DataPath/simulacao.vcd
$date
	Mon May 25 21:04:06 2026
$end
$version
	Icarus Verilog
$end
$timescale
	1ps
$end
$scope module testbench $end
$var reg 1 ! clk $end
$var reg 1 " reset $end
$var integer 32 # i [31:0] $end
$scope module dut $end
$var wire 1 ! clk $end
$var wire 1 " reset $end
$var wire 1 $ zero $end
$var wire 32 % write_data [31:0] $end
$var wire 1 & regwrite $end
$var wire 32 ' read_2 [31:0] $end
$var wire 32 ( read_1 [31:0] $end
$var wire 32 ) pc [31:0] $end
$var wire 32 * next_pc [31:0] $end
$var wire 1 + memwrite $end
$var wire 1 , memtoreg $end
$var wire 32 - memread_valor [31:0] $end
$var wire 1 . memread $end
$var wire 32 / instruction [31:0] $end
$var wire 32 0 imm_extendido [31:0] $end
$var wire 1 1 branch $end
$var wire 1 2 alusrc $end
$var wire 32 3 alusaida [31:0] $end
$var wire 32 4 alu_operando2 [31:0] $end
$var wire 2 5 aluOp [1:0] $end
$var wire 4 6 aluControl [3:0] $end
$scope module ImmGen_inst $end
$var wire 32 7 instruction [31:0] $end
$var reg 32 8 imm_extendido [31:0] $end
$upscope $end
$scope module alu $end
$var wire 1 $ zero $end
$var wire 32 9 read2_Imm [31:0] $end
$var wire 32 : read1 [31:0] $end
$var wire 4 ; alucontrol [3:0] $end
$var reg 32 < alusaida [31:0] $end
$upscope $end
$scope module alu_control $end
$var wire 3 = funct3 [2:0] $end
$var wire 1 > funct7_b30 $end
$var wire 6 ? funct [5:0] $end
$var wire 2 @ aluop [1:0] $end
$var reg 4 A alucontrol [3:0] $end
$upscope $end
$scope module banco_de_registradores $end
$var wire 1 ! clk $end
$var wire 5 B rd [4:0] $end
$var wire 5 C rs1 [4:0] $end
$var wire 5 D rs2 [4:0] $end
$var wire 32 E write_data [31:0] $end
$var wire 1 & regwrite $end
$var reg 32 F read1 [31:0] $end
$var reg 32 G read2 [31:0] $end
$var integer 32 H i [31:0] $end
$upscope $end
$scope module control $end
$var wire 7 I opcode [6:0] $end
$var reg 2 J aluop [1:0] $end
$var reg 1 2 alusrc $end
$var reg 1 1 branch $end
$var reg 1 . memread $end
$var reg 1 , memtoreg $end
$var reg 1 + memwrite $end
$var reg 1 & regwrite $end
$upscope $end
$scope module instruction_mem $end
$var wire 32 K instruction [31:0] $end
$var wire 32 L pc [31:0] $end
$upscope $end
$scope module memory_bank $end
$var wire 32 M alu_resultado [31:0] $end
$var wire 1 ! clk $end
$var wire 1 . memread $end
$var wire 1 + memwrite $end
$var wire 32 N write_data [31:0] $end
$var reg 32 O mem_read [31:0] $end
$upscope $end
$scope module mux_alusrc $end
$var wire 1 2 control $end
$var wire 32 P input1 [31:0] $end
$var wire 32 Q input2 [31:0] $end
$var reg 32 R saida [31:0] $end
$upscope $end
$scope module mux_memtoreg $end
$var wire 1 , control $end
$var wire 32 S input1 [31:0] $end
$var wire 32 T input2 [31:0] $end
$var reg 32 U saida [31:0] $end
$upscope $end
$scope module pc_module $end
$var wire 1 ! clk $end
$var wire 32 V next_pc [31:0] $end
$var wire 1 " reset $end
$var reg 32 W pc [31:0] $end
$upscope $end
$upscope $end
$upscope $end
$enddefinitions $end
$comment Show the parameter values. $end
$dumpall
$end
#0
$dumpvars
b0 W
b100 V
b111111 U
b0 T
b111111 S
b100101 R
b0 Q
b100101 P
b0 O
b100101 N
b111111 M
b0 L
b1000000011000101000001010110011 K
b10 J
b110011 I
b100000 H
b100101 G
b1100100 F
b111111 E
b110 D
b101 C
b101 B
b110 A
b10 @
b100001 ?
1>
b0 =
b111111 <
b110 ;
b1100100 :
b100101 9
b0 8
b1000000011000101000001010110011 7
b110 6
b10 5
b100101 4
b111111 3
02
01
b0 0
b1000000011000101000001010110011 /
0.
b0 -
0,
0+
b100 *
b0 )
b1100100 (
b100101 '
1&
b111111 %
0$
bx #
1"
0!
$end
#5000
b11010 %
b11010 E
b11010 U
b11010 3
b11010 <
b11010 M
b11010 S
b111111 (
b111111 :
b111111 F
1!
#10000
0!
#15000
b11111111111111111111111111110101 %
b11111111111111111111111111110101 E
b11111111111111111111111111110101 U
b11111111111111111111111111110101 3
b11111111111111111111111111110101 <
b11111111111111111111111111110101 M
b11111111111111111111111111110101 S
b11010 (
b11010 :
b11010 F
1!
#16000
0"
#20000
x$
bx %
bx E
bx U
bx 4
bx 9
bx R
bx 3
bx <
bx M
bx S
b10 6
b10 ;
b10 A
bx '
bx G
bx N
bx P
bx (
bx :
bx F
0&
b0 5
b0 @
b0 J
x>
b0xxxx ?
bx =
bx B
bx D
bx C
bx I
bx /
bx 7
bx K
b1000 *
b1000 V
b100 )
b100 L
b100 W
0!
#25000
1!
#30000
b1100 *
b1100 V
b1000 )
b1000 L
b1000 W
0!
#35000
1!
#40000
b10000 *
b10000 V
b1100 )
b1100 L
b1100 W
0!
#45000
1!
#50000
b10100 *
b10100 V
b10000 )
b10000 L
b10000 W
0!
#55000
1!
#60000
b11000 *
b11000 V
b10100 )
b10100 L
b10100 W
0!
#65000
1!
#70000
b11100 *
b11100 V
b11000 )
b11000 L
b11000 W
0!
#75000
1!
#76000
b100000 #
